datastream/__about__.py
datastream/__init__.py
datastream/base.py
datastream/deserializing.py
datastream/serializing.py
datastream/twoway.py
pydatastreams-1.3.3.dist-info/METADATA
pydatastreams-1.3.3.dist-info/WHEEL
pydatastreams-1.3.3.dist-info/licenses/LICENSE.txt
pydatastreams-1.3.3.dist-info/RECORD
