Metadata-Version: 2.3
Name: pydatastreams
Version: 1.3.3
Summary: A simple and easy to use library for reading and writing data streams.
Project-URL: Homepage, https://github.com/yntha/datastream
Project-URL: Repository, https://github.com/yntha/datastream.git
Project-URL: Issues, https://github.com/yntha/datastream/issues
Author-email: yntha <bguznvjk@gmail.com>
License-File: LICENSE.txt
Keywords: binary,data,file,io,stream
Classifier: Development Status :: 3 - Alpha
Classifier: Intended Audience :: Developers
Classifier: License :: OSI Approved :: GNU General Public License v3 or later (GPLv3+)
Classifier: Programming Language :: Python :: 3.11
Classifier: Programming Language :: Python :: 3.12
Classifier: Programming Language :: Python :: 3.13
Requires-Python: >=3.11
